rownd_django/__init__.py
rownd_django/apps.py
rownd_django/settings.py
rownd_django/auth/__init__.py
rownd_django/auth/backend.py
rownd_django/auth/cache.py
rownd_django/auth/client.py
rownd_django/auth/jwks_client.py
rownd_django/auth/urls.py
rownd_django/auth/views.py
rownd_django/tests/__init__.py
rownd_django/tests/main.py
rownd_django-1.2.1.dist-info/LICENSE
rownd_django-1.2.1.dist-info/METADATA
rownd_django-1.2.1.dist-info/WHEEL
rownd_django-1.2.1.dist-info/top_level.txt
rownd_django-1.2.1.dist-info/RECORD
