Metadata-Version: 2.1
Name: rownd_django
Version: 1.2.1
Summary: Rownd bindings for Django
Home-page: https://rownd.io
Author: Rownd, Inc.
Author-email: support@rownd.io
License: Apache 2.0
Project-URL: Documentation, https://docs.rownd.io/rownd/sdk-reference/web/django
Project-URL: Source, https://github.com/rownd/django
Classifier: Environment :: Web Environment
Classifier: Framework :: Django
Classifier: Framework :: Django :: 3.0
Classifier: Framework :: Django :: 3.1
Classifier: Framework :: Django :: 3.2
Classifier: Framework :: Django :: 4.0
Classifier: Intended Audience :: Developers
Classifier: License :: OSI Approved :: Apache Software License
Classifier: Operating System :: OS Independent
Classifier: Programming Language :: Python
Classifier: Programming Language :: Python :: 3
Classifier: Programming Language :: Python :: 3 :: Only
Classifier: Programming Language :: Python :: 3.6
Classifier: Programming Language :: Python :: 3.7
Classifier: Programming Language :: Python :: 3.8
Classifier: Programming Language :: Python :: 3.9
Classifier: Programming Language :: Python :: 3.10
Classifier: Programming Language :: Python :: 3.11
Classifier: Programming Language :: Python :: 3.12
Classifier: Programming Language :: Python :: 3.13
Classifier: Topic :: Internet :: WWW/HTTP
Classifier: Topic :: Internet :: WWW/HTTP :: Dynamic Content
Classifier: Topic :: Internet :: WWW/HTTP :: Session
Requires-Python: >=3.6
License-File: LICENSE
Requires-Dist: Django>=3.0
Requires-Dist: PyJWT>=2.3
Requires-Dist: cryptography>=36.0
Requires-Dist: requests>=2.27
